{
  "schema": "rootz.ai/company-facts/v1",
  "ticker": "AZO",
  "total_facts": 30,
  "by_type": {
    "topic_mention": 30
  },
  "facts": [
    {
      "fact_type": "topic_mention",
      "subject": "AZO",
      "predicate": "discussed_in_filing",
      "object": "Automotive",
      "value": 31,
      "unit": "mentions",
      "confidence": 0.95,
      "topic": "automotive",
      "fiscal_quarter": null,
      "fiscal_year": null
    },
    {
      "fact_type": "topic_mention",
      "subject": "AZO",
      "predicate": "discussed_in_filing",
      "object": "Automotive",
      "value": 31,
      "unit": "mentions",
      "confidence": 0.95,
      "topic": "automotive",
      "fiscal_quarter": null,
      "fiscal_year": null
    },
    {
      "fact_type": "topic_mention",
      "subject": "AZO",
      "predicate": "discussed_in_filing",
      "object": "Automotive",
      "value": 34,
      "unit": "mentions",
      "confidence": 0.95,
      "topic": "automotive",
      "fiscal_quarter": null,
      "fiscal_year": null
    },
    {
      "fact_type": "topic_mention",
      "subject": "AZO",
      "predicate": "discussed_in_filing",
      "object": "Supply Chain",
      "value": 12,
      "unit": "mentions",
      "confidence": 0.94,
      "topic": "supply_chain",
      "fiscal_quarter": null,
      "fiscal_year": null
    },
    {
      "fact_type": "topic_mention",
      "subject": "AZO",
      "predicate": "discussed_in_filing",
      "object": "Regulation",
      "value": 12,
      "unit": "mentions",
      "confidence": 0.94,
      "topic": "regulation",
      "fiscal_quarter": null,
      "fiscal_year": null
    },
    {
      "fact_type": "topic_mention",
      "subject": "AZO",
      "predicate": "discussed_in_filing",
      "object": "Supply Chain",
      "value": 12,
      "unit": "mentions",
      "confidence": 0.94,
      "topic": "supply_chain",
      "fiscal_quarter": null,
      "fiscal_year": null
    },
    {
      "fact_type": "topic_mention",
      "subject": "AZO",
      "predicate": "discussed_in_filing",
      "object": "Regulation",
      "value": 12,
      "unit": "mentions",
      "confidence": 0.94,
      "topic": "regulation",
      "fiscal_quarter": null,
      "fiscal_year": null
    },
    {
      "fact_type": "topic_mention",
      "subject": "AZO",
      "predicate": "discussed_in_filing",
      "object": "Regulation",
      "value": 12,
      "unit": "mentions",
      "confidence": 0.94,
      "topic": "regulation",
      "fiscal_quarter": null,
      "fiscal_year": null
    },
    {
      "fact_type": "topic_mention",
      "subject": "AZO",
      "predicate": "discussed_in_filing",
      "object": "Supply Chain",
      "value": 11,
      "unit": "mentions",
      "confidence": 0.9199999999999999,
      "topic": "supply_chain",
      "fiscal_quarter": null,
      "fiscal_year": null
    },
    {
      "fact_type": "topic_mention",
      "subject": "AZO",
      "predicate": "discussed_in_filing",
      "object": "AI Compute",
      "value": 9,
      "unit": "mentions",
      "confidence": 0.8799999999999999,
      "topic": "ai_compute",
      "fiscal_quarter": null,
      "fiscal_year": null
    },
    {
      "fact_type": "topic_mention",
      "subject": "AZO",
      "predicate": "discussed_in_filing",
      "object": "AI Compute",
      "value": 9,
      "unit": "mentions",
      "confidence": 0.8799999999999999,
      "topic": "ai_compute",
      "fiscal_quarter": null,
      "fiscal_year": null
    },
    {
      "fact_type": "topic_mention",
      "subject": "AZO",
      "predicate": "discussed_in_filing",
      "object": "AI Compute",
      "value": 9,
      "unit": "mentions",
      "confidence": 0.8799999999999999,
      "topic": "ai_compute",
      "fiscal_quarter": null,
      "fiscal_year": null
    },
    {
      "fact_type": "topic_mention",
      "subject": "AZO",
      "predicate": "discussed_in_filing",
      "object": "Blockchain & Crypto",
      "value": 5,
      "unit": "mentions",
      "confidence": 0.7999999999999999,
      "topic": "blockchain",
      "fiscal_quarter": null,
      "fiscal_year": null
    },
    {
      "fact_type": "topic_mention",
      "subject": "AZO",
      "predicate": "discussed_in_filing",
      "object": "Blockchain & Crypto",
      "value": 5,
      "unit": "mentions",
      "confidence": 0.7999999999999999,
      "topic": "blockchain",
      "fiscal_quarter": null,
      "fiscal_year": null
    },
    {
      "fact_type": "topic_mention",
      "subject": "AZO",
      "predicate": "discussed_in_filing",
      "object": "Blockchain & Crypto",
      "value": 5,
      "unit": "mentions",
      "confidence": 0.7999999999999999,
      "topic": "blockchain",
      "fiscal_quarter": null,
      "fiscal_year": null
    },
    {
      "fact_type": "topic_mention",
      "subject": "AZO",
      "predicate": "discussed_in_filing",
      "object": "Cybersecurity",
      "value": 3,
      "unit": "mentions",
      "confidence": 0.76,
      "topic": "cybersecurity",
      "fiscal_quarter": null,
      "fiscal_year": null
    },
    {
      "fact_type": "topic_mention",
      "subject": "AZO",
      "predicate": "discussed_in_filing",
      "object": "Sovereign & Government",
      "value": 3,
      "unit": "mentions",
      "confidence": 0.76,
      "topic": "sovereign",
      "fiscal_quarter": null,
      "fiscal_year": null
    },
    {
      "fact_type": "topic_mention",
      "subject": "AZO",
      "predicate": "discussed_in_filing",
      "object": "Cybersecurity",
      "value": 3,
      "unit": "mentions",
      "confidence": 0.76,
      "topic": "cybersecurity",
      "fiscal_quarter": null,
      "fiscal_year": null
    },
    {
      "fact_type": "topic_mention",
      "subject": "AZO",
      "predicate": "discussed_in_filing",
      "object": "Sovereign & Government",
      "value": 3,
      "unit": "mentions",
      "confidence": 0.76,
      "topic": "sovereign",
      "fiscal_quarter": null,
      "fiscal_year": null
    },
    {
      "fact_type": "topic_mention",
      "subject": "AZO",
      "predicate": "discussed_in_filing",
      "object": "Cybersecurity",
      "value": 2,
      "unit": "mentions",
      "confidence": 0.74,
      "topic": "cybersecurity",
      "fiscal_quarter": null,
      "fiscal_year": null
    },
    {
      "fact_type": "topic_mention",
      "subject": "AZO",
      "predicate": "discussed_in_filing",
      "object": "Sovereign & Government",
      "value": 2,
      "unit": "mentions",
      "confidence": 0.74,
      "topic": "sovereign",
      "fiscal_quarter": null,
      "fiscal_year": null
    },
    {
      "fact_type": "topic_mention",
      "subject": "AZO",
      "predicate": "discussed_in_filing",
      "object": "Trusted Computing",
      "value": 1,
      "unit": "mentions",
      "confidence": 0.72,
      "topic": "trusted_computing",
      "fiscal_quarter": null,
      "fiscal_year": null
    },
    {
      "fact_type": "topic_mention",
      "subject": "AZO",
      "predicate": "discussed_in_filing",
      "object": "Capital Expenditure",
      "value": 1,
      "unit": "mentions",
      "confidence": 0.72,
      "topic": "capex",
      "fiscal_quarter": null,
      "fiscal_year": null
    },
    {
      "fact_type": "topic_mention",
      "subject": "AZO",
      "predicate": "discussed_in_filing",
      "object": "Platform & Ecosystem",
      "value": 1,
      "unit": "mentions",
      "confidence": 0.72,
      "topic": "platform",
      "fiscal_quarter": null,
      "fiscal_year": null
    },
    {
      "fact_type": "topic_mention",
      "subject": "AZO",
      "predicate": "discussed_in_filing",
      "object": "Trusted Computing",
      "value": 1,
      "unit": "mentions",
      "confidence": 0.72,
      "topic": "trusted_computing",
      "fiscal_quarter": null,
      "fiscal_year": null
    },
    {
      "fact_type": "topic_mention",
      "subject": "AZO",
      "predicate": "discussed_in_filing",
      "object": "Capital Expenditure",
      "value": 1,
      "unit": "mentions",
      "confidence": 0.72,
      "topic": "capex",
      "fiscal_quarter": null,
      "fiscal_year": null
    },
    {
      "fact_type": "topic_mention",
      "subject": "AZO",
      "predicate": "discussed_in_filing",
      "object": "Platform & Ecosystem",
      "value": 1,
      "unit": "mentions",
      "confidence": 0.72,
      "topic": "platform",
      "fiscal_quarter": null,
      "fiscal_year": null
    },
    {
      "fact_type": "topic_mention",
      "subject": "AZO",
      "predicate": "discussed_in_filing",
      "object": "Trusted Computing",
      "value": 1,
      "unit": "mentions",
      "confidence": 0.72,
      "topic": "trusted_computing",
      "fiscal_quarter": null,
      "fiscal_year": null
    },
    {
      "fact_type": "topic_mention",
      "subject": "AZO",
      "predicate": "discussed_in_filing",
      "object": "Capital Expenditure",
      "value": 1,
      "unit": "mentions",
      "confidence": 0.72,
      "topic": "capex",
      "fiscal_quarter": null,
      "fiscal_year": null
    },
    {
      "fact_type": "topic_mention",
      "subject": "AZO",
      "predicate": "discussed_in_filing",
      "object": "Platform & Ecosystem",
      "value": 1,
      "unit": "mentions",
      "confidence": 0.72,
      "topic": "platform",
      "fiscal_quarter": null,
      "fiscal_year": null
    }
  ],
  "live_api": "https://origin.rootz.global/api/company/AZO/transcripts",
  "origin": {
    "leaf": "0be17d4018d8cd11d0487eba33828e41c6fd1d850c66e914a327258573f5ead5",
    "parent": "8cec3b35314c02c51a273f67a575bf7b47b93c3e3e84f709efb7d2f270fe67f6",
    "timestamp": "2026-04-12T03:13:08.458Z",
    "source": "facts:AZO",
    "chain": "SEC.gov PEM → origin.rootz.global extraction → GitHub mirror",
    "registry": "origin.rootz.global",
    "verify": "https://origin.rootz.global/api/verify/0be17d4018d8cd11d0487eba33828e41c6fd1d850c66e914a327258573f5ead5",
    "keep_alive": "Include this leaf as parent when citing this data. Verify freshness at the verify URL."
  },
  "_sync": {
    "exported_at": "2026-04-12T03:13:08.458Z",
    "server_version": "origin.rootz.global",
    "mirror": "github.com/skswave/origin-data",
    "live_api": "https://origin.rootz.global",
    "note": "This is a daily snapshot. For real-time data, search, and MCP tools, use the live API."
  }
}