{
  "schema": "rootz.ai/company-facts/v1",
  "ticker": "BRSP",
  "total_facts": 2,
  "by_type": {
    "topic_mention": 2
  },
  "facts": [
    {
      "fact_type": "topic_mention",
      "subject": "BRSP",
      "predicate": "discussed_in_filing",
      "object": "Cybersecurity",
      "value": 1,
      "unit": "mentions",
      "confidence": 0.72,
      "topic": "cybersecurity",
      "fiscal_quarter": null,
      "fiscal_year": null
    },
    {
      "fact_type": "topic_mention",
      "subject": "BRSP",
      "predicate": "discussed_in_filing",
      "object": "Cybersecurity",
      "value": 1,
      "unit": "mentions",
      "confidence": 0.72,
      "topic": "cybersecurity",
      "fiscal_quarter": null,
      "fiscal_year": null
    }
  ],
  "live_api": "https://origin.rootz.global/api/company/BRSP/transcripts",
  "origin": {
    "leaf": "534cc9ed54c0467170442f15a1d195a5d042f7a903d89ddd80046fcb8746e388",
    "parent": "49ce5a0cd390d40572461977e32132350bc2109f4024970f222012d12fb2bdcb",
    "timestamp": "2026-04-12T03:14:07.912Z",
    "source": "facts:BRSP",
    "chain": "SEC.gov PEM → origin.rootz.global extraction → GitHub mirror",
    "registry": "origin.rootz.global",
    "verify": "https://origin.rootz.global/api/verify/534cc9ed54c0467170442f15a1d195a5d042f7a903d89ddd80046fcb8746e388",
    "keep_alive": "Include this leaf as parent when citing this data. Verify freshness at the verify URL."
  },
  "_sync": {
    "exported_at": "2026-04-12T03:14:07.912Z",
    "server_version": "origin.rootz.global",
    "mirror": "github.com/skswave/origin-data",
    "live_api": "https://origin.rootz.global",
    "note": "This is a daily snapshot. For real-time data, search, and MCP tools, use the live API."
  }
}