{
  "schema": "rootz.ai/sec-company/v1",
  "ticker": "AAPI",
  "name": "Apple iSports Group, Inc.",
  "cik": "0001134982",
  "exchange": "OTC",
  "sic": "6411",
  "sic_description": "Insurance Agents, Brokers & Service",
  "state_of_incorporation": "NV",
  "headquarters": null,
  "founded": null,
  "ipo_date": null,
  "status": "active",
  "fiscal_year_end": "1231",
  "summary": ". Background Prevention Insurance.Com (the Company) was incorporated under the laws of the State of Nevada in 1975 as Vita Plus Industries, Inc. In March 1999, the Company sold its remaining inventory and changed its name to Prevention Insurance.Com. On August 31, 2023, the Company amended its Articles of Incorporation with the Nevada Secretary of State to affect the name change of the Company to Apple iSports Group, Inc. 4 Table of Contents DESCRIPTION OF OUR BUSINESS Our corporate structure is...",
  "tags": [],
  "peak_metrics": {
    "market_cap_usd": null,
    "market_cap_date": null,
    "employees": null,
    "employees_date": null,
    "rd_spend_usd": null,
    "rd_spend_year": null
  },
  "last_filing_date": null,
  "live_api": "https://origin.rootz.global/api/company/AAPI",
  "origin": {
    "leaf": "87e1462bb816b042c6c3a8149a5d916ad24fb6a55dd3a72940be911aa4bb7c70",
    "parent": "bad674b4d01ef26662b9b2590987c010d07cae9113d96eb1380f05b09c48bb26",
    "timestamp": "2026-04-12T03:12:52.643Z",
    "source": "0001477932-25-002341",
    "chain": "SEC.gov PEM → origin.rootz.global extraction → GitHub mirror",
    "registry": "origin.rootz.global",
    "verify": "https://origin.rootz.global/api/verify/87e1462bb816b042c6c3a8149a5d916ad24fb6a55dd3a72940be911aa4bb7c70",
    "keep_alive": "Include this leaf as parent when citing this data. Verify freshness at the verify URL."
  },
  "_sync": {
    "exported_at": "2026-04-12T03:12:52.643Z",
    "server_version": "origin.rootz.global",
    "mirror": "github.com/skswave/origin-data",
    "live_api": "https://origin.rootz.global",
    "note": "This is a daily snapshot. For real-time data, search, and MCP tools, use the live API."
  }
}