{
  "schema": "rootz.ai/sec-company/v1",
  "ticker": "ALDA",
  "name": "ATLANTICA INC",
  "cik": "0001062506",
  "exchange": "OTC",
  "sic": "6770",
  "sic_description": "Blank Checks",
  "state_of_incorporation": "UT",
  "headquarters": null,
  "founded": null,
  "ipo_date": null,
  "status": "active",
  "fiscal_year_end": "1231",
  "summary": null,
  "tags": [],
  "peak_metrics": {
    "market_cap_usd": null,
    "market_cap_date": null,
    "employees": null,
    "employees_date": null,
    "rd_spend_usd": null,
    "rd_spend_year": null
  },
  "last_filing_date": null,
  "live_api": "https://origin.rootz.global/api/company/ALDA",
  "origin": {
    "leaf": "0affb6677659b25c88a5c808992e57047f852f13ad65d80d37ae40a52869f73b",
    "parent": null,
    "timestamp": "2026-04-12T03:12:53.755Z",
    "source": null,
    "chain": "SEC.gov PEM → origin.rootz.global extraction → GitHub mirror",
    "registry": "origin.rootz.global",
    "verify": "https://origin.rootz.global/api/verify/0affb6677659b25c88a5c808992e57047f852f13ad65d80d37ae40a52869f73b",
    "keep_alive": "Include this leaf as parent when citing this data. Verify freshness at the verify URL."
  },
  "_sync": {
    "exported_at": "2026-04-12T03:12:53.755Z",
    "server_version": "origin.rootz.global",
    "mirror": "github.com/skswave/origin-data",
    "live_api": "https://origin.rootz.global",
    "note": "This is a daily snapshot. For real-time data, search, and MCP tools, use the live API."
  }
}