{
  "schema": "rootz.ai/sec-company/v1",
  "ticker": "CHGG",
  "name": "CHEGG, INC",
  "cik": "0001364954",
  "exchange": "NYSE",
  "sic": "8200",
  "sic_description": "Services-Educational Services",
  "state_of_incorporation": "DE",
  "headquarters": null,
  "founded": null,
  "ipo_date": null,
  "status": "active",
  "fiscal_year_end": "1231",
  "summary": "PART I Overview Chegg is a learning platform helping businesses bring new skills to their workforce and giving lifelong learners and students the skills and confidence to succeed. Focused on the large and growing skilling market, Chegg offers innovative tools for workplace readiness, professional upskilling, and language learning. Chegg also continues to offer students artificial intelligence (AI)-driven, personalized support. Chegg remains committed to its mission of improving learning outcomes...",
  "tags": [],
  "peak_metrics": {
    "market_cap_usd": null,
    "market_cap_date": null,
    "employees": null,
    "employees_date": null,
    "rd_spend_usd": null,
    "rd_spend_year": null
  },
  "last_filing_date": null,
  "live_api": "https://origin.rootz.global/api/company/CHGG",
  "origin": {
    "leaf": "601b9aa44baa6ca64f18785bf59020d71129d385b152c64f5b111497b3250df2",
    "parent": "2461abf86ecfffdd889730f57bc52ad32f660af1a5b815dea98ea725d5464c75",
    "timestamp": "2026-04-12T03:12:52.294Z",
    "source": "0001364954-26-000021",
    "chain": "SEC.gov PEM → origin.rootz.global extraction → GitHub mirror",
    "registry": "origin.rootz.global",
    "verify": "https://origin.rootz.global/api/verify/601b9aa44baa6ca64f18785bf59020d71129d385b152c64f5b111497b3250df2",
    "keep_alive": "Include this leaf as parent when citing this data. Verify freshness at the verify URL."
  },
  "_sync": {
    "exported_at": "2026-04-12T03:12:52.294Z",
    "server_version": "origin.rootz.global",
    "mirror": "github.com/skswave/origin-data",
    "live_api": "https://origin.rootz.global",
    "note": "This is a daily snapshot. For real-time data, search, and MCP tools, use the live API."
  }
}