{
  "schema": "rootz.ai/sec-profile/v1",
  "ticker": "BBDC",
  "name": "Barings BDC, Inc.",
  "cik": "0001379785",
  "summary": "PARTI . Organization We are a Maryland corporation incorporated on October10, 2006. We currently operate as a closed-end, non-diversified investment company and have elected to be treated as a business development company (BDC) under the Investment Company Act of 1940, as amended (the 1940 Act). We have elected for federal income tax purposes to be treated and intend to qualify annually as a regulated investment company (RIC) under Subchapter M of the Internal Revenue Code of 1986, as amended (t...",
  "live_api": "https://origin.rootz.global/api/company/BBDC/profile",
  "origin": {
    "leaf": "eba8a8b9637b0bab0e7f6bdfcde2302ea2c7050c1f42d0949e79a855be4dace7",
    "parent": "6c9f6e131e9c5ddb5ef376120d9f739ce1f62f05e7f286501c7288433344c944",
    "timestamp": "2026-04-13T06:15:07.171Z",
    "source": "profile:0001379785",
    "chain": "SEC.gov PEM → origin.rootz.global extraction → GitHub mirror",
    "registry": "origin.rootz.global",
    "verify": "https://origin.rootz.global/api/verify/eba8a8b9637b0bab0e7f6bdfcde2302ea2c7050c1f42d0949e79a855be4dace7",
    "keep_alive": "Include this leaf as parent when citing this data. Verify freshness at the verify URL."
  },
  "_sync": {
    "exported_at": "2026-04-13T06:15:07.171Z",
    "server_version": "origin.rootz.global",
    "mirror": "github.com/skswave/origin-data",
    "live_api": "https://origin.rootz.global",
    "note": "This is a daily snapshot. For real-time data, search, and MCP tools, use the live API."
  }
}