{
  "schema": "rootz.ai/sec-profile/v1",
  "ticker": "CNNE",
  "name": "Cannae Holdings, Inc.",
  "cik": "0001704720",
  "summary": "PARTI Introductory Note The following describes the business of Cannae Holdings, Inc. and its subsidiaries. Except where otherwise noted, all references to \"we,\" \"us,\" \"our,\" \"Cannae,\" \"Cannae Holdings\" or the \"Company,\" are to Cannae Holdings, Inc. and its subsidiaries, taken together. Description of Business We primarily acquire interests in operating companies and are engaged in actively managing and operating a core group of those companies, which we are committed to supporting for the long ...",
  "live_api": "https://origin.rootz.global/api/company/CNNE/profile",
  "origin": {
    "leaf": "557447c796fd59b9e797cd393e17e7b253260942635d6749ff62e2e325341c62",
    "parent": "58a567129b57818a83ecbe0958d9ed5a3e4b76f49e96f293ab5bb50887f27e84",
    "timestamp": "2026-04-12T03:12:56.283Z",
    "source": "profile:0001704720",
    "chain": "SEC.gov PEM → origin.rootz.global extraction → GitHub mirror",
    "registry": "origin.rootz.global",
    "verify": "https://origin.rootz.global/api/verify/557447c796fd59b9e797cd393e17e7b253260942635d6749ff62e2e325341c62",
    "keep_alive": "Include this leaf as parent when citing this data. Verify freshness at the verify URL."
  },
  "_sync": {
    "exported_at": "2026-04-12T03:12:56.283Z",
    "server_version": "origin.rootz.global",
    "mirror": "github.com/skswave/origin-data",
    "live_api": "https://origin.rootz.global",
    "note": "This is a daily snapshot. For real-time data, search, and MCP tools, use the live API."
  }
}